pylanggetter/__init__.py
pylanggetter/__main__.py
pylanggetter/pylanggetter.py
pylanggetter/utils.py
pylanggetter-0.4.0.dist-info/entry_points.txt
pylanggetter-0.4.0.dist-info/METADATA
pylanggetter-0.4.0.dist-info/WHEEL
pylanggetter-0.4.0.dist-info/RECORD
