Metadata-Version: 2.3
Name: PylangGetter
Version: 0.4.0
Summary: Tiny utility to help you download Dofus Retro Lang files
Keywords: dofus retro,dofus,retro,bot,emulateur
Author: Dysta
Requires-Python: >=3.8
Classifier: Programming Language :: Python :: 3
Classifier: Programming Language :: Python :: 3.8
Classifier: Programming Language :: Python :: 3.9
Classifier: Programming Language :: Python :: 3.10
Classifier: Programming Language :: Python :: 3.11
Classifier: Programming Language :: Python :: 3.12
Classifier: Programming Language :: Python :: 3.13
Requires-Dist: loguru (>=0.6.0,<0.7.0)
Project-URL: Repository, https://github.com/Dysta/PylangGetter
